pyNTCIREVAL/__init__.py
pyNTCIREVAL/labeler.py
pyNTCIREVAL/main.py
pyNTCIREVAL/utils.py
pyNTCIREVAL/metrics/__init__.py
pyNTCIREVAL/metrics/ap.py
pyNTCIREVAL/metrics/err.py
pyNTCIREVAL/metrics/grade_metric.py
pyNTCIREVAL/metrics/hit.py
pyNTCIREVAL/metrics/metric.py
pyNTCIREVAL/metrics/ms_ndcg.py
pyNTCIREVAL/metrics/ncu.py
pyNTCIREVAL/metrics/ndcg.py
pyNTCIREVAL/metrics/nerr.py
pyNTCIREVAL/metrics/normalized_metric.py
pyNTCIREVAL/metrics/o_measure.py
pyNTCIREVAL/metrics/p_measure.py
pyNTCIREVAL/metrics/p_plus_measure.py
pyNTCIREVAL/metrics/precision.py
pyNTCIREVAL/metrics/q_measure.py
pyNTCIREVAL/metrics/rbp.py
pyNTCIREVAL/metrics/rr.py
pyNTCIREVAL-0.0.3.dist-info/METADATA
pyNTCIREVAL-0.0.3.dist-info/RECORD
pyNTCIREVAL-0.0.3.dist-info/WHEEL
pyNTCIREVAL-0.0.3.dist-info/entry_points.txt
pyNTCIREVAL-0.0.3.dist-info/top_level.txt
