Metadata-Version: 2.1
Name: pyNTCIREVAL
Version: 0.0.3
Summary: Python version of NTCIREVAL
Home-page: https://github.com/mpkato/pyNTCIREVAL
Author: Makoto P. Kato
Author-email: mpkato@slis.tsukuba.ac.jp
License: MIT License
Keywords: information retrieval,evaluation
Platform: UNKNOWN
Classifier: Programming Language :: Python :: 3.6
Requires-Dist: numpy
Requires-Dist: click
